app/__init__.py
app/main.py
app/ml_models.py
morea-0.1.0.dist-info/licenses/LICENSE
morea-0.1.0.dist-info/METADATA
morea-0.1.0.dist-info/WHEEL
morea-0.1.0.dist-info/entry_points.txt
morea-0.1.0.dist-info/top_level.txt
morea-0.1.0.dist-info/RECORD
