Metadata-Version: 2.4
Name: morea
Version: 0.1.0
Summary: A RESTful API for deploying machine learning models quickly.
Home-page: https://github.com/Chrimetz/MoReA
Author: Christopher A. Metz
Author-email: cmetz@uni-bremen.de
License: Apache License 2.0
Classifier: Programming Language :: Python :: 3
Classifier: License :: OSI Approved :: Apache Software License
Classifier: Operating System :: OS Independent
Classifier: Development Status :: 4 - Beta
Classifier: Intended Audience :: Developers
Classifier: Topic :: Software Development :: Libraries :: Application Frameworks
Requires-Python: >=3.7
License-File: LICENSE
Requires-Dist: uvicorn
Requires-Dist: numpy
Requires-Dist: fastapi
Requires-Dist: onnxruntime==1.21.0
Requires-Dist: pydantic
Requires-Dist: coremltools
Requires-Dist: scikit-learn
Requires-Dist: requests
Dynamic: author
Dynamic: author-email
Dynamic: classifier
Dynamic: description
Dynamic: description-content-type
Dynamic: home-page
Dynamic: license
Dynamic: license-file
Dynamic: requires-dist
Dynamic: requires-python
Dynamic: summary
